livekit/plugins/voxist/__init__.py
livekit/plugins/voxist/audio_processor.py
livekit/plugins/voxist/connection_pool.py
livekit/plugins/voxist/exceptions.py
livekit/plugins/voxist/log.py
livekit/plugins/voxist/models.py
livekit/plugins/voxist/stream.py
livekit/plugins/voxist/stt.py
livekit/plugins/voxist/version.py
livekit_plugins_voxist-0.9.1.dist-info/licenses/LICENSE
livekit_plugins_voxist-0.9.1.dist-info/METADATA
livekit_plugins_voxist-0.9.1.dist-info/WHEEL
livekit_plugins_voxist-0.9.1.dist-info/top_level.txt
livekit_plugins_voxist-0.9.1.dist-info/RECORD
