Metadata-Version: 2.4
Name: livekit-plugins-voxist
Version: 0.9.1
Summary: LiveKit STT plugin for Voxist ASR with ultra-low latency connection pooling
Author-email: Voxist <contact@voxist.com>
License: MIT
Project-URL: Homepage, https://github.com/voxist/livekit-plugins-voxist
Project-URL: Documentation, https://github.com/voxist/livekit-plugins-voxist#readme
Project-URL: Repository, https://github.com/voxist/livekit-plugins-voxist
Project-URL: Issues, https://github.com/voxist/livekit-plugins-voxist/issues
Keywords: livekit,stt,speech-to-text,asr,voxist,real-time,voice-ai
Classifier: Development Status :: 4 - Beta
Classifier: Intended Audience :: Developers
Classifier: License :: OSI Approved :: MIT License
Classifier: Programming Language :: Python :: 3
Classifier: Programming Language :: Python :: 3.10
Classifier: Programming Language :: Python :: 3.11
Classifier: Programming Language :: Python :: 3.12
Classifier: Topic :: Multimedia :: Sound/Audio :: Speech
Classifier: Topic :: Scientific/Engineering :: Artificial Intelligence
Requires-Python: >=3.10
License-File: LICENSE
Requires-Dist: livekit-agents>=0.8.0
Requires-Dist: aiohttp>=3.9.0
Requires-Dist: numpy>=1.24.0
Provides-Extra: dev
Requires-Dist: pytest>=7.4.0; extra == "dev"
Requires-Dist: pytest-asyncio>=0.21.0; extra == "dev"
Requires-Dist: pytest-cov>=4.1.0; extra == "dev"
Requires-Dist: pytest-benchmark>=4.0.0; extra == "dev"
Requires-Dist: black>=23.0.0; extra == "dev"
Requires-Dist: ruff>=0.1.0; extra == "dev"
Requires-Dist: mypy>=1.5.0; extra == "dev"
Dynamic: license-file
